blueprints/__init__.py
blueprints/math_helpers.py
blueprints/tree_structure.md
blueprints/type_alias.py
blueprints/unit_conversion.py
blueprints/validations.py
blueprints/checks/__init__.py
blueprints/checks/nominal_concrete_cover/__init__.py
blueprints/checks/nominal_concrete_cover/nominal_concrete_cover.py
blueprints/codes/__init__.py
blueprints/codes/formula.py
blueprints/codes/latex_formula.py
blueprints/codes/cur/__init__.py
blueprints/codes/cur/cur_228/__init__.py
blueprints/codes/cur/cur_228/formula_2_21.py
blueprints/codes/cur/cur_228/formula_2_22.py
blueprints/codes/eurocode/__init__.py
blueprints/codes/eurocode/en_1992_1_1_2004/__init__.py
blueprints/codes/eurocode/en_1992_1_1_2004/chapter_10_precast_concrete_elements_and_structures/__init__.py
blueprints/codes/eurocode/en_1992_1_1_2004/chapter_11_lightweight_aggregate_concrete_structures/__init__.py
blueprints/codes/eurocode/en_1992_1_1_2004/chapter_12_plain_and_lightly_reinforced_concrete_structures/__init__.py
blueprints/codes/eurocode/en_1992_1_1_2004/chapter_12_plain_and_lightly_reinforced_concrete_structures/formula_12_1.py
blueprints/codes/eurocode/en_1992_1_1_2004/chapter_12_plain_and_lightly_reinforced_concrete_structures/formula_12_2.py
blueprints/codes/eurocode/en_1992_1_1_2004/chapter_12_plain_and_lightly_reinforced_concrete_structures/formula_12_3.py
blueprints/codes/eurocode/en_1992_1_1_2004/chapter_12_plain_and_lightly_reinforced_concrete_structures/formula_12_4.py
blueprints/codes/eurocode/en_1992_1_1_2004/chapter_12_plain_and_lightly_reinforced_concrete_structures/formula_12_5_6.py
blueprints/codes/eurocode/en_1992_1_1_2004/chapter_3_materials/__init__.py
blueprints/codes/eurocode/en_1992_1_1_2004/chapter_3_materials/formula_3_1.py
blueprints/codes/eurocode/en_1992_1_1_2004/chapter_3_materials/formula_3_10.py
blueprints/codes/eurocode/en_1992_1_1_2004/chapter_3_materials/formula_3_11.py
blueprints/codes/eurocode/en_1992_1_1_2004/chapter_3_materials/formula_3_12.py
blue_prints-0.5.2.dist-info/METADATA
blue_prints-0.5.2.dist-info/WHEEL
blue_prints-0.5.2.dist-info/licenses/LICENSE
blue_prints-0.5.2.dist-info/RECORD
