Metadata-Version: 2.4
Name: blue-prints
Version: 0.5.2
Summary: Blueprints, open source python package for civil engineering calculations.
Project-URL: homepage, https://blueprints.readthedocs.io
Project-URL: documentation, https://blueprints.readthedocs.io
Project-URL: repository, https://github.com/Blueprints-org/blueprints
Project-URL: issues, https://github.com/Blueprints-org/blueprints/issues
Project-URL: changelog, https://github.com/Blueprints-org/blueprints/releases
Author: Blueprints
Maintainer: Blueprints Maintainers
Maintainer-email: Enrique García Méndez <enriquegarcia@live.nl>
License: MIT
License-File: LICENSE
Keywords: Civil engineering,Eurocodes,European building codes,Material properties,Structural analysis,Structural engineering
Classifier: Intended Audience :: Science/Research
Classifier: License :: OSI Approved :: MIT License
Classifier: Programming Language :: Python :: 3.11
Classifier: Topic :: Scientific/Engineering
Classifier: Topic :: Software Development :: Libraries :: Python Modules
Requires-Python: >=3.12
Requires-Dist: matplotlib>=3.10.7
Requires-Dist: numpy>=1.25.2
Requires-Dist: sectionproperties>=3.8.0
Requires-Dist: shapely>=2.0.1
